<!--
Licensed Materials - Property of IBM
IBM Sterling Selling and Fulfillment Suite - Foundation
(C) Copyright IBM Corp. 2010, 2012 All Rights Reserved.
US Government Users Restricted Rights - Use, duplication or disclosure restricted by GSA ADP Schedule Contract with IBM Corp.
-->
<YFS_Item_Service_AssocList>
    <ItemServiceAssoc HoldSchedTillCompletion="N"
        ItemKey="2009061714264120484" PricingProductQuantity="0.00"
        PricingServiceQuantity="0.00" ProductQuantity="1.00"
        ServiceItemDesc="Delivery" ServiceItemGroupCode="DS"
        ServiceItemId="Delivery"
        ServiceOrganizationCode="#{Generic_Enterprise_Code}"
        ServiceQuantity="1.00" ServiceUOM="UNIT" TimeOffsetInMinutes="0.00"/>
    <ItemServiceAssoc HoldSchedTillCompletion="N"
        ItemKey="2009062921513927991" PricingProductQuantity="0.00"
        PricingServiceQuantity="0.00" ProductQuantity="1.00"
        ServiceItemDesc="Delivery" ServiceItemGroupCode="DS"
        ServiceItemId="Delivery"
        ServiceOrganizationCode="#{Generic_Enterprise_Code}"
        ServiceQuantity="1.00" ServiceUOM="UNIT" TimeOffsetInMinutes="0.00"/>
    <ItemServiceAssoc HoldSchedTillCompletion="N"
        ItemKey="2009062921581128062" PricingProductQuantity="0.00"
        PricingServiceQuantity="0.00" ProductQuantity="1.00"
        ServiceItemDesc="Delivery" ServiceItemGroupCode="DS"
        ServiceItemId="Delivery"
        ServiceOrganizationCode="#{Generic_Enterprise_Code}"
        ServiceQuantity="1.00" ServiceUOM="UNIT" TimeOffsetInMinutes="0.00"/>
    <ItemServiceAssoc HoldSchedTillCompletion="N"
        ItemKey="2009062922014628069" PricingProductQuantity="0.00"
        PricingServiceQuantity="0.00" ProductQuantity="1.00"
        ServiceItemDesc="Delivery" ServiceItemGroupCode="DS"
        ServiceItemId="Delivery"
        ServiceOrganizationCode="#{Generic_Enterprise_Code}"
        ServiceQuantity="1.00" ServiceUOM="UNIT" TimeOffsetInMinutes="0.00"/>
    <ItemServiceAssoc HoldSchedTillCompletion="N"
        ItemKey="2009062922034428079" PricingProductQuantity="0.00"
        PricingServiceQuantity="0.00" ProductQuantity="1.00"
        ServiceItemDesc="Delivery" ServiceItemGroupCode="DS"
        ServiceItemId="Delivery"
        ServiceOrganizationCode="#{Generic_Enterprise_Code}"
        ServiceQuantity="1.00" ServiceUOM="UNIT" TimeOffsetInMinutes="0.00"/>
    <ItemServiceAssoc HoldSchedTillCompletion="N"
        ItemKey="2009070910460948121" PricingProductQuantity="0.00"
        PricingServiceQuantity="0.00" ProductQuantity="1.00"
        ServiceItemDesc="Delivery" ServiceItemGroupCode="DS"
        ServiceItemId="Delivery"
        ServiceOrganizationCode="#{Generic_Enterprise_Code}"
        ServiceQuantity="1.00" ServiceUOM="UNIT" TimeOffsetInMinutes="0.00"/>
    <ItemServiceAssoc HoldSchedTillCompletion="N"
        ItemKey="2009092215252744381" PricingProductQuantity="0.00"
        PricingServiceQuantity="0.00" ProductQuantity="1.00"
        ServiceItemDesc="Delivery" ServiceItemGroupCode="DS"
        ServiceItemId="Delivery"
        ServiceOrganizationCode="#{Generic_Enterprise_Code}"
        ServiceQuantity="1.00" ServiceUOM="UNIT" TimeOffsetInMinutes="0.00"/>
    <ItemServiceAssoc HoldSchedTillCompletion="N"
        ItemKey="2009092215482144574" PricingProductQuantity="0.00"
        PricingServiceQuantity="0.00" ProductQuantity="1.00"
        ServiceItemDesc="Delivery" ServiceItemGroupCode="DS"
        ServiceItemId="Delivery"
        ServiceOrganizationCode="#{Generic_Enterprise_Code}"
        ServiceQuantity="1.00" ServiceUOM="UNIT" TimeOffsetInMinutes="0.00"/>
    <ItemServiceAssoc HoldSchedTillCompletion="N"
        ItemKey="2009092216435344680" PricingProductQuantity="0.00"
        PricingServiceQuantity="0.00" ProductQuantity="1.00"
        ServiceItemDesc="Delivery" ServiceItemGroupCode="DS"
        ServiceItemId="Delivery"
        ServiceOrganizationCode="#{Generic_Enterprise_Code}"
        ServiceQuantity="1.00" ServiceUOM="UNIT" TimeOffsetInMinutes="0.00"/>
    <ItemServiceAssoc HoldSchedTillCompletion="N"
        ItemKey="2009092321224345541" PricingProductQuantity="0.00"
        PricingServiceQuantity="0.00" ProductQuantity="1.00"
        ServiceItemDesc="Delivery" ServiceItemGroupCode="DS"
        ServiceItemId="Delivery"
        ServiceOrganizationCode="#{Generic_Enterprise_Code}"
        ServiceQuantity="1.00" ServiceUOM="UNIT" TimeOffsetInMinutes="0.00"/>
    <ItemServiceAssoc HoldSchedTillCompletion="N"
        ItemKey="2009092322063545815" PricingProductQuantity="0.00"
        PricingServiceQuantity="0.00" ProductQuantity="1.00"
        ServiceItemDesc="Delivery" ServiceItemGroupCode="DS"
        ServiceItemId="Delivery"
        ServiceOrganizationCode="#{Generic_Enterprise_Code}"
        ServiceQuantity="1.00" ServiceUOM="UNIT" TimeOffsetInMinutes="0.00"/>
    <ItemServiceAssoc HoldSchedTillCompletion="N"
        ItemKey="2009092322083145847" PricingProductQuantity="0.00"
        PricingServiceQuantity="0.00" ProductQuantity="1.00"
        ServiceItemDesc="Delivery" ServiceItemGroupCode="DS"
        ServiceItemId="Delivery"
        ServiceOrganizationCode="#{Generic_Enterprise_Code}"
        ServiceQuantity="1.00" ServiceUOM="UNIT" TimeOffsetInMinutes="0.00"/>
    <ItemServiceAssoc HoldSchedTillCompletion="N"
        ItemKey="2009092322363246096" PricingProductQuantity="0.00"
        PricingServiceQuantity="0.00" ProductQuantity="1.00"
        ServiceItemDesc="Delivery" ServiceItemGroupCode="DS"
        ServiceItemId="Delivery"
        ServiceOrganizationCode="#{Generic_Enterprise_Code}"
        ServiceQuantity="1.00" ServiceUOM="UNIT" TimeOffsetInMinutes="0.00"/>
    <ItemServiceAssoc HoldSchedTillCompletion="N"
        ItemKey="2009092322430446219" PricingProductQuantity="0.00"
        PricingServiceQuantity="0.00" ProductQuantity="1.00"
        ServiceItemDesc="Delivery" ServiceItemGroupCode="DS"
        ServiceItemId="Delivery"
        ServiceOrganizationCode="#{Generic_Enterprise_Code}"
        ServiceQuantity="1.00" ServiceUOM="UNIT" TimeOffsetInMinutes="0.00"/>
    <ItemServiceAssoc HoldSchedTillCompletion="N"
        ItemKey="2009092419585254280" PricingProductQuantity="0.00"
        PricingServiceQuantity="0.00" ProductQuantity="1.00"
        ServiceItemDesc="Delivery" ServiceItemGroupCode="DS"
        ServiceItemId="Delivery"
        ServiceOrganizationCode="#{Generic_Enterprise_Code}"
        ServiceQuantity="1.00" ServiceUOM="UNIT" TimeOffsetInMinutes="0.00"/>
    <ItemServiceAssoc HoldSchedTillCompletion="N"
        ItemKey="2009093023495957109" PricingProductQuantity="0.00"
        PricingServiceQuantity="0.00" ProductQuantity="1.00"
        ServiceItemDesc="Delivery" ServiceItemGroupCode="DS"
        ServiceItemId="Delivery"
        ServiceOrganizationCode="#{Generic_Enterprise_Code}"
        ServiceQuantity="1.00" ServiceUOM="UNIT" TimeOffsetInMinutes="0.00"/>
    <ItemServiceAssoc HoldSchedTillCompletion="N"
        ItemKey="2009093023582157233" PricingProductQuantity="0.00"
        PricingServiceQuantity="0.00" ProductQuantity="1.00"
        ServiceItemDesc="Delivery" ServiceItemGroupCode="DS"
        ServiceItemId="Delivery"
        ServiceOrganizationCode="#{Generic_Enterprise_Code}"
        ServiceQuantity="1.00" ServiceUOM="UNIT" TimeOffsetInMinutes="0.00"/>
    <ItemServiceAssoc HoldSchedTillCompletion="N"
        ItemKey="2009093023595057240" PricingProductQuantity="0.00"
        PricingServiceQuantity="0.00" ProductQuantity="1.00"
        ServiceItemDesc="Delivery" ServiceItemGroupCode="DS"
        ServiceItemId="Delivery"
        ServiceOrganizationCode="#{Generic_Enterprise_Code}"
        ServiceQuantity="1.00" ServiceUOM="UNIT" TimeOffsetInMinutes="0.00"/>
    <ItemServiceAssoc HoldSchedTillCompletion="N"
        ItemKey="2009100100012057247" PricingProductQuantity="0.00"
        PricingServiceQuantity="0.00" ProductQuantity="1.00"
        ServiceItemDesc="Delivery" ServiceItemGroupCode="DS"
        ServiceItemId="Delivery"
        ServiceOrganizationCode="#{Generic_Enterprise_Code}"
        ServiceQuantity="1.00" ServiceUOM="UNIT" TimeOffsetInMinutes="0.00"/>
    <ItemServiceAssoc HoldSchedTillCompletion="N"
        ItemKey="2009100100023057254" PricingProductQuantity="0.00"
        PricingServiceQuantity="0.00" ProductQuantity="1.00"
        ServiceItemDesc="Delivery" ServiceItemGroupCode="DS"
        ServiceItemId="Delivery"
        ServiceOrganizationCode="#{Generic_Enterprise_Code}"
        ServiceQuantity="1.00" ServiceUOM="UNIT" TimeOffsetInMinutes="0.00"/>
    <ItemServiceAssoc HoldSchedTillCompletion="N"
        ItemKey="2009100100055457277" PricingProductQuantity="0.00"
        PricingServiceQuantity="0.00" ProductQuantity="1.00"
        ServiceItemDesc="Delivery" ServiceItemGroupCode="DS"
        ServiceItemId="Delivery"
        ServiceOrganizationCode="#{Generic_Enterprise_Code}"
        ServiceQuantity="1.00" ServiceUOM="UNIT" TimeOffsetInMinutes="0.00"/>
    <ItemServiceAssoc HoldSchedTillCompletion="N"
        ItemKey="2009101923213967188" PricingProductQuantity="0.00"
        PricingServiceQuantity="0.00" ProductQuantity="1.00"
        ServiceItemDesc="Delivery" ServiceItemGroupCode="DS"
        ServiceItemId="Delivery"
        ServiceOrganizationCode="#{Generic_Enterprise_Code}"
        ServiceQuantity="1.00" ServiceUOM="UNIT" TimeOffsetInMinutes="0.00"/>
    <ItemServiceAssoc HoldSchedTillCompletion="N"
        ItemKey="2009102012152867458" PricingProductQuantity="0.00"
        PricingServiceQuantity="0.00" ProductQuantity="1.00"
        ServiceItemDesc="Delivery" ServiceItemGroupCode="DS"
        ServiceItemId="Delivery"
        ServiceOrganizationCode="#{Generic_Enterprise_Code}"
        ServiceQuantity="1.00" ServiceUOM="UNIT" TimeOffsetInMinutes="0.00"/>
    <ItemServiceAssoc HoldSchedTillCompletion="N"
        ItemKey="2009102012193267469" PricingProductQuantity="0.00"
        PricingServiceQuantity="0.00" ProductQuantity="1.00"
        ServiceItemDesc="Delivery" ServiceItemGroupCode="DS"
        ServiceItemId="Delivery"
        ServiceOrganizationCode="#{Generic_Enterprise_Code}"
        ServiceQuantity="1.00" ServiceUOM="UNIT" TimeOffsetInMinutes="0.00"/>
    <ItemServiceAssoc HoldSchedTillCompletion="N"
        ItemKey="2009121216551699119" PricingProductQuantity="0.00"
        PricingServiceQuantity="0.00" ProductQuantity="1.00"
        ServiceItemDesc="Delivery" ServiceItemGroupCode="DS"
        ServiceItemId="Delivery"
        ServiceOrganizationCode="#{Generic_Enterprise_Code}"
        ServiceQuantity="1.00" ServiceUOM="UNIT" TimeOffsetInMinutes="0.00"/>
    <ItemServiceAssoc HoldSchedTillCompletion="N"
        ItemKey="2009121216584199130" PricingProductQuantity="0.00"
        PricingServiceQuantity="0.00" ProductQuantity="1.00"
        ServiceItemDesc="Delivery" ServiceItemGroupCode="DS"
        ServiceItemId="Delivery"
        ServiceOrganizationCode="#{Generic_Enterprise_Code}"
        ServiceQuantity="1.00" ServiceUOM="UNIT" TimeOffsetInMinutes="0.00"/>
    <ItemServiceAssoc HoldSchedTillCompletion="N"
        ItemKey="2009121217022099254" PricingProductQuantity="0.00"
        PricingServiceQuantity="0.00" ProductQuantity="1.00"
        ServiceItemDesc="Delivery" ServiceItemGroupCode="DS"
        ServiceItemId="Delivery"
        ServiceOrganizationCode="#{Generic_Enterprise_Code}"
        ServiceQuantity="1.00" ServiceUOM="UNIT" TimeOffsetInMinutes="0.00"/>
    <ItemServiceAssoc HoldSchedTillCompletion="N"
        ItemKey="2009121217041599265" PricingProductQuantity="0.00"
        PricingServiceQuantity="0.00" ProductQuantity="1.00"
        ServiceItemDesc="Delivery" ServiceItemGroupCode="DS"
        ServiceItemId="Delivery"
        ServiceOrganizationCode="#{Generic_Enterprise_Code}"
        ServiceQuantity="1.00" ServiceUOM="UNIT" TimeOffsetInMinutes="0.00"/>
    <ItemServiceAssoc HoldSchedTillCompletion="N"
        ItemKey="2009121217061899273" PricingProductQuantity="0.00"
        PricingServiceQuantity="0.00" ProductQuantity="1.00"
        ServiceItemDesc="Delivery" ServiceItemGroupCode="DS"
        ServiceItemId="Delivery"
        ServiceOrganizationCode="#{Generic_Enterprise_Code}"
        ServiceQuantity="1.00" ServiceUOM="UNIT" TimeOffsetInMinutes="0.00"/>
    <ItemServiceAssoc HoldSchedTillCompletion="N"
        ItemKey="2009121217255499506" PricingProductQuantity="0.00"
        PricingServiceQuantity="0.00" ProductQuantity="1.00"
        ServiceItemDesc="Delivery" ServiceItemGroupCode="DS"
        ServiceItemId="Delivery"
        ServiceOrganizationCode="#{Generic_Enterprise_Code}"
        ServiceQuantity="1.00" ServiceUOM="UNIT" TimeOffsetInMinutes="0.00"/>
    <ItemServiceAssoc HoldSchedTillCompletion="N"
        ItemKey="2009121217283999514" PricingProductQuantity="0.00"
        PricingServiceQuantity="0.00" ProductQuantity="1.00"
        ServiceItemDesc="Delivery" ServiceItemGroupCode="DS"
        ServiceItemId="Delivery"
        ServiceOrganizationCode="#{Generic_Enterprise_Code}"
        ServiceQuantity="1.00" ServiceUOM="UNIT" TimeOffsetInMinutes="0.00"/>
    <ItemServiceAssoc HoldSchedTillCompletion="N"
        ItemKey="2009121217320899621" PricingProductQuantity="0.00"
        PricingServiceQuantity="0.00" ProductQuantity="1.00"
        ServiceItemDesc="Delivery" ServiceItemGroupCode="DS"
        ServiceItemId="Delivery"
        ServiceOrganizationCode="#{Generic_Enterprise_Code}"
        ServiceQuantity="1.00" ServiceUOM="UNIT" TimeOffsetInMinutes="0.00"/>
    <ItemServiceAssoc HoldSchedTillCompletion="N"
        ItemKey="2009121217335799632" PricingProductQuantity="0.00"
        PricingServiceQuantity="0.00" ProductQuantity="1.00"
        ServiceItemDesc="Delivery" ServiceItemGroupCode="DS"
        ServiceItemId="Delivery"
        ServiceOrganizationCode="#{Generic_Enterprise_Code}"
        ServiceQuantity="1.00" ServiceUOM="UNIT" TimeOffsetInMinutes="0.00"/>
    <ItemServiceAssoc HoldSchedTillCompletion="N"
        ItemKey="2009121217374999643" PricingProductQuantity="0.00"
        PricingServiceQuantity="0.00" ProductQuantity="1.00"
        ServiceItemDesc="Delivery" ServiceItemGroupCode="DS"
        ServiceItemId="Delivery"
        ServiceOrganizationCode="#{Generic_Enterprise_Code}"
        ServiceQuantity="1.00" ServiceUOM="UNIT" TimeOffsetInMinutes="0.00"/>
    <ItemServiceAssoc HoldSchedTillCompletion="N"
        ItemKey="2009121217433399730" PricingProductQuantity="0.00"
        PricingServiceQuantity="0.00" ProductQuantity="1.00"
        ServiceItemDesc="Delivery" ServiceItemGroupCode="DS"
        ServiceItemId="Delivery"
        ServiceOrganizationCode="#{Generic_Enterprise_Code}"
        ServiceQuantity="1.00" ServiceUOM="UNIT" TimeOffsetInMinutes="0.00"/>
    <ItemServiceAssoc HoldSchedTillCompletion="N"
        ItemKey="2009121217461899741" PricingProductQuantity="0.00"
        PricingServiceQuantity="0.00" ProductQuantity="1.00"
        ServiceItemDesc="Delivery" ServiceItemGroupCode="DS"
        ServiceItemId="Delivery"
        ServiceOrganizationCode="#{Generic_Enterprise_Code}"
        ServiceQuantity="1.00" ServiceUOM="UNIT" TimeOffsetInMinutes="0.00"/>
    <ItemServiceAssoc HoldSchedTillCompletion="N"
        ItemKey="2009121217482799752" PricingProductQuantity="0.00"
        PricingServiceQuantity="0.00" ProductQuantity="1.00"
        ServiceItemDesc="Delivery" ServiceItemGroupCode="DS"
        ServiceItemId="Delivery"
        ServiceOrganizationCode="#{Generic_Enterprise_Code}"
        ServiceQuantity="1.00" ServiceUOM="UNIT" TimeOffsetInMinutes="0.00"/>
    <ItemServiceAssoc HoldSchedTillCompletion="N"
        ItemKey="2009121217515999839" PricingProductQuantity="0.00"
        PricingServiceQuantity="0.00" ProductQuantity="1.00"
        ServiceItemDesc="Delivery" ServiceItemGroupCode="DS"
        ServiceItemId="Delivery"
        ServiceOrganizationCode="#{Generic_Enterprise_Code}"
        ServiceQuantity="1.00" ServiceUOM="UNIT" TimeOffsetInMinutes="0.00"/>
    <ItemServiceAssoc HoldSchedTillCompletion="N"
        ItemKey="2009121218154299955" PricingProductQuantity="0.00"
        PricingServiceQuantity="0.00" ProductQuantity="1.00"
        ServiceItemDesc="Delivery" ServiceItemGroupCode="DS"
        ServiceItemId="Delivery"
        ServiceOrganizationCode="#{Generic_Enterprise_Code}"
        ServiceQuantity="1.00" ServiceUOM="UNIT" TimeOffsetInMinutes="0.00"/>
    <ItemServiceAssoc HoldSchedTillCompletion="N"
        ItemKey="2009121218184199963" PricingProductQuantity="0.00"
        PricingServiceQuantity="0.00" ProductQuantity="1.00"
        ServiceItemDesc="Delivery" ServiceItemGroupCode="DS"
        ServiceItemId="Delivery"
        ServiceOrganizationCode="#{Generic_Enterprise_Code}"
        ServiceQuantity="1.00" ServiceUOM="UNIT" TimeOffsetInMinutes="0.00"/>
    <ItemServiceAssoc HoldSchedTillCompletion="N"
        ItemKey="20091212183540100050" PricingProductQuantity="0.00"
        PricingServiceQuantity="0.00" ProductQuantity="1.00"
        ServiceItemDesc="Delivery" ServiceItemGroupCode="DS"
        ServiceItemId="Delivery"
        ServiceOrganizationCode="#{Generic_Enterprise_Code}"
        ServiceQuantity="1.00" ServiceUOM="UNIT" TimeOffsetInMinutes="0.00"/>
    <ItemServiceAssoc HoldSchedTillCompletion="N"
        ItemKey="20091212192748100439" PricingProductQuantity="0.00"
        PricingServiceQuantity="0.00" ProductQuantity="1.00"
        ServiceItemDesc="Delivery" ServiceItemGroupCode="DS"
        ServiceItemId="Delivery"
        ServiceOrganizationCode="#{Generic_Enterprise_Code}"
        ServiceQuantity="1.00" ServiceUOM="UNIT" TimeOffsetInMinutes="0.00"/>
    <ItemServiceAssoc HoldSchedTillCompletion="N"
        ItemKey="20091212192912100447" PricingProductQuantity="0.00"
        PricingServiceQuantity="0.00" ProductQuantity="1.00"
        ServiceItemDesc="Delivery" ServiceItemGroupCode="DS"
        ServiceItemId="Delivery"
        ServiceOrganizationCode="#{Generic_Enterprise_Code}"
        ServiceQuantity="1.00" ServiceUOM="UNIT" TimeOffsetInMinutes="0.00"/>
    <ItemServiceAssoc HoldSchedTillCompletion="N"
        ItemKey="20091212193102100577" PricingProductQuantity="0.00"
        PricingServiceQuantity="0.00" ProductQuantity="1.00"
        ServiceItemDesc="Delivery" ServiceItemGroupCode="DS"
        ServiceItemId="Delivery"
        ServiceOrganizationCode="#{Generic_Enterprise_Code}"
        ServiceQuantity="1.00" ServiceUOM="UNIT" TimeOffsetInMinutes="0.00"/>
    <ItemServiceAssoc HoldSchedTillCompletion="N"
        ItemKey="20091212200521100688" PricingProductQuantity="0.00"
        PricingServiceQuantity="0.00" ProductQuantity="1.00"
        ServiceItemDesc="Delivery" ServiceItemGroupCode="DS"
        ServiceItemId="Delivery"
        ServiceOrganizationCode="#{Generic_Enterprise_Code}"
        ServiceQuantity="1.00" ServiceUOM="UNIT" TimeOffsetInMinutes="0.00"/>
    <ItemServiceAssoc HoldSchedTillCompletion="N"
        ItemKey="20091212200936100699" PricingProductQuantity="0.00"
        PricingServiceQuantity="0.00" ProductQuantity="1.00"
        ServiceItemDesc="Delivery" ServiceItemGroupCode="DS"
        ServiceItemId="Delivery"
        ServiceOrganizationCode="#{Generic_Enterprise_Code}"
        ServiceQuantity="1.00" ServiceUOM="UNIT" TimeOffsetInMinutes="0.00"/>
    <ItemServiceAssoc HoldSchedTillCompletion="N"
        ItemKey="20091212201254100807" PricingProductQuantity="0.00"
        PricingServiceQuantity="0.00" ProductQuantity="1.00"
        ServiceItemDesc="Delivery" ServiceItemGroupCode="DS"
        ServiceItemId="Delivery"
        ServiceOrganizationCode="#{Generic_Enterprise_Code}"
        ServiceQuantity="1.00" ServiceUOM="UNIT" TimeOffsetInMinutes="0.00"/>
    <ItemServiceAssoc HoldSchedTillCompletion="N"
        ItemKey="20091212201603100818" PricingProductQuantity="0.00"
        PricingServiceQuantity="0.00" ProductQuantity="1.00"
        ServiceItemDesc="Delivery" ServiceItemGroupCode="DS"
        ServiceItemId="Delivery"
        ServiceOrganizationCode="#{Generic_Enterprise_Code}"
        ServiceQuantity="1.00" ServiceUOM="UNIT" TimeOffsetInMinutes="0.00"/>
    <ItemServiceAssoc HoldSchedTillCompletion="N"
        ItemKey="20091212202137100921" PricingProductQuantity="0.00"
        PricingServiceQuantity="0.00" ProductQuantity="1.00"
        ServiceItemDesc="Delivery" ServiceItemGroupCode="DS"
        ServiceItemId="Delivery"
        ServiceOrganizationCode="#{Generic_Enterprise_Code}"
        ServiceQuantity="1.00" ServiceUOM="UNIT" TimeOffsetInMinutes="0.00"/>
    <ItemServiceAssoc HoldSchedTillCompletion="N"
        ItemKey="20091212202444100929" PricingProductQuantity="0.00"
        PricingServiceQuantity="0.00" ProductQuantity="1.00"
        ServiceItemDesc="Delivery" ServiceItemGroupCode="DS"
        ServiceItemId="Delivery"
        ServiceOrganizationCode="#{Generic_Enterprise_Code}"
        ServiceQuantity="1.00" ServiceUOM="UNIT" TimeOffsetInMinutes="0.00"/>
    <ItemServiceAssoc HoldSchedTillCompletion="N"
        ItemKey="20091212203123101036" PricingProductQuantity="0.00"
        PricingServiceQuantity="0.00" ProductQuantity="1.00"
        ServiceItemDesc="Delivery" ServiceItemGroupCode="DS"
        ServiceItemId="Delivery"
        ServiceOrganizationCode="#{Generic_Enterprise_Code}"
        ServiceQuantity="1.00" ServiceUOM="UNIT" TimeOffsetInMinutes="0.00"/>
    <ItemServiceAssoc HoldSchedTillCompletion="N"
        ItemKey="20091212203333101047" PricingProductQuantity="0.00"
        PricingServiceQuantity="0.00" ProductQuantity="1.00"
        ServiceItemDesc="Delivery" ServiceItemGroupCode="DS"
        ServiceItemId="Delivery"
        ServiceOrganizationCode="#{Generic_Enterprise_Code}"
        ServiceQuantity="1.00" ServiceUOM="UNIT" TimeOffsetInMinutes="0.00"/>
    <ItemServiceAssoc HoldSchedTillCompletion="N"
        ItemKey="20091212203728101055" PricingProductQuantity="0.00"
        PricingServiceQuantity="0.00" ProductQuantity="1.00"
        ServiceItemDesc="Delivery" ServiceItemGroupCode="DS"
        ServiceItemId="Delivery"
        ServiceOrganizationCode="#{Generic_Enterprise_Code}"
        ServiceQuantity="1.00" ServiceUOM="UNIT" TimeOffsetInMinutes="0.00"/>
    <ItemServiceAssoc HoldSchedTillCompletion="N"
        ItemKey="20091212203908101063" PricingProductQuantity="0.00"
        PricingServiceQuantity="0.00" ProductQuantity="1.00"
        ServiceItemDesc="Delivery" ServiceItemGroupCode="DS"
        ServiceItemId="Delivery"
        ServiceOrganizationCode="#{Generic_Enterprise_Code}"
        ServiceQuantity="1.00" ServiceUOM="UNIT" TimeOffsetInMinutes="0.00"/>
    <ItemServiceAssoc HoldSchedTillCompletion="N"
        ItemKey="20091212204030101147" PricingProductQuantity="0.00"
        PricingServiceQuantity="0.00" ProductQuantity="1.00"
        ServiceItemDesc="Delivery" ServiceItemGroupCode="DS"
        ServiceItemId="Delivery"
        ServiceOrganizationCode="#{Generic_Enterprise_Code}"
        ServiceQuantity="1.00" ServiceUOM="UNIT" TimeOffsetInMinutes="0.00"/>
    <ItemServiceAssoc HoldSchedTillCompletion="N"
        ItemKey="20091212204155101155" PricingProductQuantity="0.00"
        PricingServiceQuantity="0.00" ProductQuantity="1.00"
        ServiceItemDesc="Delivery" ServiceItemGroupCode="DS"
        ServiceItemId="Delivery"
        ServiceOrganizationCode="#{Generic_Enterprise_Code}"
        ServiceQuantity="1.00" ServiceUOM="UNIT" TimeOffsetInMinutes="0.00"/>
    <ItemServiceAssoc HoldSchedTillCompletion="N"
        ItemKey="20100106202705125216" PricingProductQuantity="0.00"
        PricingServiceQuantity="0.00" ProductQuantity="1.00"
        ServiceItemDesc="Delivery" ServiceItemGroupCode="DS"
        ServiceItemId="Delivery"
        ServiceOrganizationCode="#{Generic_Enterprise_Code}"
        ServiceQuantity="1.00" ServiceUOM="UNIT" TimeOffsetInMinutes="0.00"/>
    <ItemServiceAssoc HoldSchedTillCompletion="N"
        ItemKey="20100106203049125227" PricingProductQuantity="0.00"
        PricingServiceQuantity="0.00" ProductQuantity="1.00"
        ServiceItemDesc="Delivery" ServiceItemGroupCode="DS"
        ServiceItemId="Delivery"
        ServiceOrganizationCode="#{Generic_Enterprise_Code}"
        ServiceQuantity="1.00" ServiceUOM="UNIT" TimeOffsetInMinutes="0.00"/>
    <ItemServiceAssoc HoldSchedTillCompletion="N"
        ItemKey="20100106203430125326" PricingProductQuantity="0.00"
        PricingServiceQuantity="0.00" ProductQuantity="1.00"
        ServiceItemDesc="Delivery" ServiceItemGroupCode="DS"
        ServiceItemId="Delivery"
        ServiceOrganizationCode="#{Generic_Enterprise_Code}"
        ServiceQuantity="1.00" ServiceUOM="UNIT" TimeOffsetInMinutes="0.00"/>
    <ItemServiceAssoc HoldSchedTillCompletion="N"
        ItemKey="20100112145657160524" PricingProductQuantity="0.00"
        PricingServiceQuantity="0.00" ProductQuantity="1.00"
        ServiceItemDesc="Delivery" ServiceItemGroupCode="DS"
        ServiceItemId="Delivery"
        ServiceOrganizationCode="#{Generic_Enterprise_Code}"
        ServiceQuantity="1.00" ServiceUOM="UNIT" TimeOffsetInMinutes="0.00"/>
    <ItemServiceAssoc HoldSchedTillCompletion="N"
        ItemKey="20100113194700185714" PricingProductQuantity="0.00"
        PricingServiceQuantity="0.00" ProductQuantity="1.00"
        ServiceItemDesc="Delivery" ServiceItemGroupCode="DS"
        ServiceItemId="Delivery"
        ServiceOrganizationCode="#{Generic_Enterprise_Code}"
        ServiceQuantity="1.00" ServiceUOM="UNIT" TimeOffsetInMinutes="0.00"/>
    <ItemServiceAssoc HoldSchedTillCompletion="N"
        ItemKey="20100113195437185846" PricingProductQuantity="0.00"
        PricingServiceQuantity="0.00" ProductQuantity="1.00"
        ServiceItemDesc="Delivery" ServiceItemGroupCode="DS"
        ServiceItemId="Delivery"
        ServiceOrganizationCode="#{Generic_Enterprise_Code}"
        ServiceQuantity="1.00" ServiceUOM="UNIT" TimeOffsetInMinutes="0.00"/>
    <ItemServiceAssoc HoldSchedTillCompletion="N"
        ItemKey="20100113195705185863" PricingProductQuantity="0.00"
        PricingServiceQuantity="0.00" ProductQuantity="1.00"
        ServiceItemDesc="Delivery" ServiceItemGroupCode="DS"
        ServiceItemId="Delivery"
        ServiceOrganizationCode="#{Generic_Enterprise_Code}"
        ServiceQuantity="1.00" ServiceUOM="UNIT" TimeOffsetInMinutes="0.00"/>
    <ItemServiceAssoc HoldSchedTillCompletion="N"
        ItemKey="20100113195903185871" PricingProductQuantity="0.00"
        PricingServiceQuantity="0.00" ProductQuantity="1.00"
        ServiceItemDesc="Delivery" ServiceItemGroupCode="DS"
        ServiceItemId="Delivery"
        ServiceOrganizationCode="#{Generic_Enterprise_Code}"
        ServiceQuantity="1.00" ServiceUOM="UNIT" TimeOffsetInMinutes="0.00"/>
    <ItemServiceAssoc HoldSchedTillCompletion="N"
        ItemKey="20100113200533186041" PricingProductQuantity="0.00"
        PricingServiceQuantity="0.00" ProductQuantity="1.00"
        ServiceItemDesc="Delivery" ServiceItemGroupCode="DS"
        ServiceItemId="Delivery"
        ServiceOrganizationCode="#{Generic_Enterprise_Code}"
        ServiceQuantity="1.00" ServiceUOM="UNIT" TimeOffsetInMinutes="0.00"/>
    <ItemServiceAssoc HoldSchedTillCompletion="N"
        ItemKey="20100113200657186052" PricingProductQuantity="0.00"
        PricingServiceQuantity="0.00" ProductQuantity="1.00"
        ServiceItemDesc="Delivery" ServiceItemGroupCode="DS"
        ServiceItemId="Delivery"
        ServiceOrganizationCode="#{Generic_Enterprise_Code}"
        ServiceQuantity="1.00" ServiceUOM="UNIT" TimeOffsetInMinutes="0.00"/>
    <ItemServiceAssoc HoldSchedTillCompletion="N"
        ItemKey="20100113200858186066" PricingProductQuantity="0.00"
        PricingServiceQuantity="0.00" ProductQuantity="1.00"
        ServiceItemDesc="Delivery" ServiceItemGroupCode="DS"
        ServiceItemId="Delivery"
        ServiceOrganizationCode="#{Generic_Enterprise_Code}"
        ServiceQuantity="1.00" ServiceUOM="UNIT" TimeOffsetInMinutes="0.00"/>
    <ItemServiceAssoc HoldSchedTillCompletion="N"
        ItemKey="20100113202253186551" PricingProductQuantity="0.00"
        PricingServiceQuantity="0.00" ProductQuantity="1.00"
        ServiceItemDesc="Delivery" ServiceItemGroupCode="DS"
        ServiceItemId="Delivery"
        ServiceOrganizationCode="#{Generic_Enterprise_Code}"
        ServiceQuantity="1.00" ServiceUOM="UNIT" TimeOffsetInMinutes="0.00"/>
    <ItemServiceAssoc HoldSchedTillCompletion="N"
        ItemKey="20100113203356186696" PricingProductQuantity="0.00"
        PricingServiceQuantity="0.00" ProductQuantity="1.00"
        ServiceItemDesc="Delivery" ServiceItemGroupCode="DS"
        ServiceItemId="Delivery"
        ServiceOrganizationCode="#{Generic_Enterprise_Code}"
        ServiceQuantity="1.00" ServiceUOM="UNIT" TimeOffsetInMinutes="0.00"/>
    <ItemServiceAssoc HoldSchedTillCompletion="N"
        ItemKey="20100113220513188954" PricingProductQuantity="0.00"
        PricingServiceQuantity="0.00" ProductQuantity="1.00"
        ServiceItemDesc="Delivery" ServiceItemGroupCode="DS"
        ServiceItemId="Delivery"
        ServiceOrganizationCode="#{Generic_Enterprise_Code}"
        ServiceQuantity="1.00" ServiceUOM="UNIT" TimeOffsetInMinutes="0.00"/>
    <ItemServiceAssoc HoldSchedTillCompletion="N"
        ItemKey="20100113220644188963" PricingProductQuantity="0.00"
        PricingServiceQuantity="0.00" ProductQuantity="1.00"
        ServiceItemDesc="Delivery" ServiceItemGroupCode="DS"
        ServiceItemId="Delivery"
        ServiceOrganizationCode="#{Generic_Enterprise_Code}"
        ServiceQuantity="1.00" ServiceUOM="UNIT" TimeOffsetInMinutes="0.00"/>
    <ItemServiceAssoc HoldSchedTillCompletion="N"
        ItemKey="20100115184544307003" PricingProductQuantity="0.00"
        PricingServiceQuantity="0.00" ProductQuantity="1.00"
        ServiceItemDesc="Delivery" ServiceItemGroupCode="DS"
        ServiceItemId="Delivery"
        ServiceOrganizationCode="#{Generic_Enterprise_Code}"
        ServiceQuantity="1.00" ServiceUOM="UNIT" TimeOffsetInMinutes="0.00"/>
    <ItemServiceAssoc HoldSchedTillCompletion="N"
        ItemKey="20100115185219307256" PricingProductQuantity="0.00"
        PricingServiceQuantity="0.00" ProductQuantity="1.00"
        ServiceItemDesc="Delivery" ServiceItemGroupCode="DS"
        ServiceItemId="Delivery"
        ServiceOrganizationCode="#{Generic_Enterprise_Code}"
        ServiceQuantity="1.00" ServiceUOM="UNIT" TimeOffsetInMinutes="0.00"/>
    <ItemServiceAssoc HoldSchedTillCompletion="N"
        ItemKey="20100115185450307421" PricingProductQuantity="0.00"
        PricingServiceQuantity="0.00" ProductQuantity="1.00"
        ServiceItemDesc="Delivery" ServiceItemGroupCode="DS"
        ServiceItemId="Delivery"
        ServiceOrganizationCode="#{Generic_Enterprise_Code}"
        ServiceQuantity="1.00" ServiceUOM="UNIT" TimeOffsetInMinutes="0.00"/>
    <ItemServiceAssoc HoldSchedTillCompletion="N"
        ItemKey="20100115193433310081" PricingProductQuantity="0.00"
        PricingServiceQuantity="0.00" ProductQuantity="1.00"
        ServiceItemDesc="Delivery" ServiceItemGroupCode="DS"
        ServiceItemId="Delivery"
        ServiceOrganizationCode="#{Generic_Enterprise_Code}"
        ServiceQuantity="1.00" ServiceUOM="UNIT" TimeOffsetInMinutes="0.00"/>
    <ItemServiceAssoc HoldSchedTillCompletion="N"
        ItemKey="20100115193731311695" PricingProductQuantity="0.00"
        PricingServiceQuantity="0.00" ProductQuantity="1.00"
        ServiceItemDesc="Delivery" ServiceItemGroupCode="DS"
        ServiceItemId="Delivery"
        ServiceOrganizationCode="#{Generic_Enterprise_Code}"
        ServiceQuantity="1.00" ServiceUOM="UNIT" TimeOffsetInMinutes="0.00"/>
    <ItemServiceAssoc HoldSchedTillCompletion="N"
        ItemKey="20100115193850312377" PricingProductQuantity="0.00"
        PricingServiceQuantity="0.00" ProductQuantity="1.00"
        ServiceItemDesc="Delivery" ServiceItemGroupCode="DS"
        ServiceItemId="Delivery"
        ServiceOrganizationCode="#{Generic_Enterprise_Code}"
        ServiceQuantity="1.00" ServiceUOM="UNIT" TimeOffsetInMinutes="0.00"/>
    <ItemServiceAssoc HoldSchedTillCompletion="N"
        ItemKey="20100115194014313160" PricingProductQuantity="0.00"
        PricingServiceQuantity="0.00" ProductQuantity="1.00"
        ServiceItemDesc="Delivery" ServiceItemGroupCode="DS"
        ServiceItemId="Delivery"
        ServiceOrganizationCode="#{Generic_Enterprise_Code}"
        ServiceQuantity="1.00" ServiceUOM="UNIT" TimeOffsetInMinutes="0.00"/>
    <ItemServiceAssoc HoldSchedTillCompletion="N"
        ItemKey="20100115194204314235" PricingProductQuantity="0.00"
        PricingServiceQuantity="0.00" ProductQuantity="1.00"
        ServiceItemDesc="Delivery" ServiceItemGroupCode="DS"
        ServiceItemId="Delivery"
        ServiceOrganizationCode="#{Generic_Enterprise_Code}"
        ServiceQuantity="1.00" ServiceUOM="UNIT" TimeOffsetInMinutes="0.00"/>
    <ItemServiceAssoc HoldSchedTillCompletion="N"
        ItemKey="#{Generic_Enterprise_Code}_IK5"
        PricingProductQuantity="0.00" PricingServiceQuantity="0.00"
        ProductQuantity="1.00" ServiceItemDesc="Delivery"
        ServiceItemGroupCode="DS" ServiceItemId="Delivery"
        ServiceOrganizationCode="#{Generic_Enterprise_Code}"
        ServiceQuantity="1.00" ServiceUOM="UNIT" TimeOffsetInMinutes="0.00"/>
</YFS_Item_Service_AssocList>

